pyroll/linear_thermal_expansion.py
pyroll_linear_thermal_expansion-3.0.0.dist-info/METADATA
pyroll_linear_thermal_expansion-3.0.0.dist-info/WHEEL
pyroll_linear_thermal_expansion-3.0.0.dist-info/licenses/LICENSE
pyroll_linear_thermal_expansion-3.0.0.dist-info/RECORD
